{
    "id": "adafruit",
    "platformid": "codal",
    "nickname": "circuitplayground",
    "name": "Adafruit Circuit Playground Express",
    "title": "Adafruit Circuit Playground Express - Blocks / Javascript editor",
    "description": "A Blocks / JavaScript code editor for the Adafruit Circuit Playground Express.",
    "corepkg": "circuit-playground",
    "bundleddirs": [
        "libs/core",
        "libs/accelerometer",
        "libs/music",
        "libs/microphone",
        "libs/lightsensor",
        "libs/temperature",
        "libs/light",
        "libs/touch",
        "libs/switch",
        "libs/circuit-playground"
    ],
    "serial": {
        "useHF2": true,
        "log": true
    },
    "simulator": {
        "autoRun": true,
        "streams": true,
        "aspectRatio": 1.0,
        "parts": false,
        "enableTrace": true,
        "boardDefinition": {
            "visual": "circuitplayground",
            "gpioPinBlocks": [
                [
                    "P0"
                ],
                [
                    "P1"
                ],
                [
                    "P2"
                ],
                [
                    "P3"
                ],
                [
                    "P4",
                    "P5",
                    "P6",
                    "P7"
                ],
                [
                    "P8",
                    "P9",
                    "P10",
                    "P11",
                    "P12"
                ],
                [
                    "P16"
                ]
            ],
            "gpioPinMap": {
                "P0": "P0",
                "P1": "P1",
                "P2": "P2",
                "P3": "P3",
                "P4": "P4",
                "P5": "P5",
                "P6": "P6",
                "P7": "P7",
                "P8": "P8",
                "P9": "P9",
                "P10": "P10",
                "P11": "P11",
                "P12": "P12",
                "P13": "P13",
                "P14": "P14",
                "P15": "P15",
                "P16": "P16",
                "P19": "P19",
                "P20": "P20"
            },
            "i2cPins": {
                "SDA": "P2",
                "SCL": "P3"
            },
            "analogInPins": [
                "A0",
                "A4",
                "A5"
            ],
            "groundPins": [
                "GND_0",
                "GND_1",
                "GND_2"
            ],
            "threeVoltPins": [
                "PWR_0",
                "PWR_2"
            ],
            "attachPowerOnRight": true,
            "onboardComponents": [
                "accelerometer",
                "buttonpair",
                "speaker",
                "thermometer",
                "rgbsensor",
                "lightsensor",
                "microphone"
            ],
            "useCrocClips": true,
            "marginWhenBreadboarding": [
                0,
                0,
                80,
                0
            ]
        }
    },
    "cloud": {
        "workspace": false,
        "packages": true,
        "sharing": true,
        "publishing": true,
        "importing": true,
        "preferredPackages": [],
        "githubPackages": true
    },
    "compile": {
        "isNative": true,
        "useUF2": true,
        "hasHex": true,
        "deployDrives": ".*",
        "deployFileMarker": "INFO_UF2.TXT",
        "driveName": "CPLAYBOOT",
        "openocdScript": "source [find interface/cmsis-dap.cfg]; set CHIPNAME at91samd21g18; source [find target/at91samdXX.cfg]",
        "flashChecksumAddr": 8368,
        "flashCodeAlign": 256,
        "taggedInts": true,
        "upgrades": [
            {
                "type": "package",
                "map": {
                    "neopixel": "light",
                    "adafruit": "circuit-playground"
                }
            }
        ]
    },
    "runtime": {
        "mathBlocks": true,
        "loopsBlocks": true,
        "logicBlocks": true,
        "variablesBlocks": true,
        "textBlocks": true,
        "onStartNamespace": "loops",
        "onStartColor": "#40bf4a"

    },
    "compileService": {
        "yottaTarget": "adafruit-cp-g18a",
        "yottaBinary": "pxt-samd.hex",
        "yottaCorePackage": "codal",
        "yottaConfig": {
            "pxt": {
                "board": {
                    "id": "BOARD_ID_CPLAY"
                }
            }
        },        
        "githubCorePackage": "lancaster-university/codal",
        "gittag": "v0.1.1",
        "serviceId": "codalcp"
    },
    "appTheme": {
        "accentColor": "#0089BF",
        "logoUrl": "https://adafruit.com/circuitplaygroundpxt",
        "logo": "./static/logo.svg",
        "docsLogo": "./static/logo.square.svg",
        "portraitLogo": "./static/logo.square.svg",
        "footerLogo": "./static/logo.square.svg",
        "cardLogo": "./static/icons/android-chrome-192x192.png",
        "appLogo": "./static/icons/android-chrome-192x192.png",
        "organization": "Microsoft MakeCode",
        "organizationUrl": "https://makecode.com/",
        "organizationLogo": "./static/Microsoft-logo_rgb_c-gray-square.png",
        "organizationWideLogo": "./static/Microsoft-logo_rgb_c-white.png",
        "homeUrl": "https://makecode.adafruit.com/",
        "embedUrl": "https://makecode.adafruit.com/",
        "legacyDomain": "pxt.adafruit.com",
        "privacyUrl": "https://go.microsoft.com/fwlink/?LinkId=521839",
        "termsOfUseUrl": "https://go.microsoft.com/fwlink/?LinkID=206977",
        "githubUrl": "https://github.com/Microsoft/pxt-adafruit",
        "boardName": "Adafruit Circuit Playground Express",
        "docMenu": [
            {
                "name": "About",
                "path": "/about"
            },
            {
                "name": "Projects",
                "path": "/projects"
            },
            {
                "name": "Examples",
                "path": "/examples"
            },
            {
                "name": "Blocks",
                "path": "/blocks"
            },
            {
                "name": "JavaScript",
                "path": "/javascript"
            },
            {
                "name": "Reference",
                "path": "/reference"
            }
        ],
        "galleries": {
            "Projects": "projects",
            "Examples": "examples"
        },        
        "sideDoc": "tutorials/getting-started",
        "invertedMenu": true,
        "invertedToolbox": true,
        "invertedMonaco": true,
        "monacoToolbox": true,
        "simAnimationEnter": "roll in",
        "simAnimationExit": "roll out",
        "exampleGallery": "examples",
        "hasAudio": true,
        "usbHelp": [],
        "extendEditor": true,
        "disableBlockIcons": true,
        "blocklyOptions": {
            "grid": {
                "spacing": 20,
                "length": 2,
                "colour": "rgba(189, 195, 199, 0.20)",
                "snap": true
            }
        },
        "blockColors": {
            "loops": "#40bf4a",
            "logic": "#4cbfe6",
            "math": "#9966ff",
            "variables": "#FF6680",
            "text": "#ffab19",
            "advanced": "#00272B"
        }
    }
}
